{"susieR": {"1_d_r": null, "0.99_d_r": null, "0.95_d_r": null, "0.9_d_r": null, "0.8_d_r": null, "0.7_d_r": 0.15, "0.5_d_r": 0.9, "0.2_d_r": 0.95, "1_tp": 17, "0.99_tp": 19, "0.95_tp": 19, "0.9_tp": 19, "0.8_tp": 19, "0.7_tp": 19, "0.5_tp": 19, "0.2_tp": 19, "1_fp": 13, "0.99_fp": 75, "0.95_fp": 92, "0.9_fp": 100, "0.8_fp": 109, "0.7_fp": 114, "0.5_fp": 123, "0.2_fp": 142}, "bolt_cheat": {"1_d_r": 0.05, "0.99_d_r": 0.05, "0.95_d_r": 0.05, "0.9_d_r": 0.05, "0.8_d_r": 0.95, "0.7_d_r": 0.95, "0.5_d_r": 0.95, "0.2_d_r": 0.95, "1_tp": 19, "0.99_tp": 19, "0.95_tp": 19, "0.9_tp": 19, "0.8_tp": 19, "0.7_tp": 19, "0.5_tp": 19, "0.2_tp": 19, "1_fp": 3, "0.99_fp": 4, "0.95_fp": 4, "0.9_fp": 4, "0.8_fp": 4, "0.7_fp": 4, "0.5_fp": 4, "0.2_fp": 6}, "susie_cheat_casusal": {"1_d_r": 0.15, "0.99_d_r": 0.15, "0.95_d_r": 0.95, "0.9_d_r": 0.95, "0.8_d_r": 0.95, "0.7_d_r": 0.95, "0.5_d_r": 0.95, "0.2_d_r": 0.95, "1_tp": 15, "0.99_tp": 19, "0.95_tp": 19, "0.9_tp": 19, "0.8_tp": 19, "0.7_tp": 19, "0.5_tp": 19, "0.2_tp": 19, "1_fp": 1, "0.99_fp": 1, "0.95_fp": 1, "0.9_fp": 1, "0.8_fp": 1, "0.7_fp": 1, "0.5_fp": 1, "0.2_fp": 1}, "bolt_no_cheat": {"1_d_r": 0.1, "0.99_d_r": 0.1, "0.95_d_r": 0.1, "0.9_d_r": 0.1, "0.8_d_r": 0.45, "0.7_d_r": 1.0, "0.5_d_r": 1.0, "0.2_d_r": 1.0, "1_tp": 20, "0.99_tp": 20, "0.95_tp": 20, "0.9_tp": 20, "0.8_tp": 20, "0.7_tp": 20, "0.5_tp": 20, "0.2_tp": 20, "1_fp": 6, "0.99_fp": 17, "0.95_fp": 18, "0.9_fp": 20, "0.8_fp": 21, "0.7_fp": 22, "0.5_fp": 23, "0.2_fp": 32}, "finemap": {"1_d_r": 0.2, "0.99_d_r": 0.2, "0.95_d_r": 0.2, "0.9_d_r": 0.2, "0.8_d_r": 0.2, "0.7_d_r": 0.3, "0.5_d_r": 0.95, "0.2_d_r": 0.95, "1_tp": 18, "0.99_tp": 19, "0.95_tp": 19, "0.9_tp": 19, "0.8_tp": 19, "0.7_tp": 19, "0.5_tp": 19, "0.2_tp": 19, "1_fp": 9, "0.99_fp": 31, "0.95_fp": 43, "0.9_fp": 47, "0.8_fp": 51, "0.7_fp": 55, "0.5_fp": 68, "0.2_fp": 91}, "finemap_cheat_casual": {"1_d_r": 0.35, "0.99_d_r": 0.35, "0.95_d_r": 0.95, "0.9_d_r": 0.95, "0.8_d_r": 0.95, "0.7_d_r": 0.95, "0.5_d_r": 0.95, "0.2_d_r": 1.0, "1_tp": 18, "0.99_tp": 19, "0.95_tp": 19, "0.9_tp": 19, "0.8_tp": 19, "0.7_tp": 19, "0.5_tp": 19, "0.2_tp": 19, "1_fp": 1, "0.99_fp": 1, "0.95_fp": 1, "0.9_fp": 1, "0.8_fp": 1, "0.7_fp": 1, "0.5_fp": 1, "0.2_fp": 1}, "gwas": {"1_d_r": 0.1, "0.99_d_r": 0.1, "0.95_d_r": 0.1, "0.9_d_r": 0.1, "0.8_d_r": 0.1, "0.7_d_r": 0.15, "0.5_d_r": 0.55, "0.2_d_r": 1.0}}